orloj/__init__.py
orloj/core.py
orloj-0.1.4.dist-info/LICENSE
orloj-0.1.4.dist-info/METADATA
orloj-0.1.4.dist-info/WHEEL
orloj-0.1.4.dist-info/RECORD
