Metadata-Version: 2.1
Name: orloj
Version: 0.1.4
Summary: Scheduler middleware for ASGI frameworks
License: MIT
Keywords: asgi,blacksheep,fastapi,litestar,quart,sanic,starlette,uvicorn
Author: Sitt Guruvanich
Author-email: aekazitt+github@gmail.com
Requires-Python: >=3.8,<4.0
Classifier: Development Status :: 3 - Alpha
Classifier: Environment :: Web Environment
Classifier: Framework :: AsyncIO
Classifier: Intended Audience :: Developers
Classifier: License :: OSI Approved :: MIT License
Classifier: Operating System :: OS Independent
Classifier: Programming Language :: Python
Classifier: Programming Language :: Python :: 3
Classifier: Programming Language :: Python :: 3.8
Classifier: Programming Language :: Python :: 3.9
Classifier: Programming Language :: Python :: 3.10
Classifier: Programming Language :: Python :: 3.11
Classifier: Programming Language :: Python :: 3.12
Classifier: Programming Language :: Python :: 3 :: Only
Classifier: Topic :: Internet :: WWW/HTTP :: Dynamic Content
Classifier: Typing :: Typed
Requires-Dist: APScheduler (>=4.0.0a5,<5.0.0)
Requires-Dist: starlette (<0.37.2)
